llama_index/packs/retry_engine_weaviate/__init__.py
llama_index/packs/retry_engine_weaviate/base.py
llama_index_packs_retry_engine_weaviate-0.5.1.dist-info/METADATA
llama_index_packs_retry_engine_weaviate-0.5.1.dist-info/WHEEL
llama_index_packs_retry_engine_weaviate-0.5.1.dist-info/licenses/LICENSE
llama_index_packs_retry_engine_weaviate-0.5.1.dist-info/RECORD
