Metadata-Version: 2.4
Name: llama-index-packs-retry-engine-weaviate
Version: 0.5.1
Summary: llama-index packs retry_engine_weaviate integration
Author-email: Your Name <you@example.com>
Maintainer: erika-cardenas
License-Expression: MIT
License-File: LICENSE
Keywords: engine,retry,weaviate
Requires-Python: <4.0,>=3.9
Requires-Dist: llama-index-vector-stores-weaviate<2,>=1.2.0
Requires-Dist: weaviate-client<5,>=4.7.1
